oxigrad-0.3.2.dist-info/METADATA
oxigrad-0.3.2.dist-info/WHEEL
oxigrad-0.3.2.dist-info/entry_points.txt
oxigrad-0.3.2.dist-info/licenses/LICENSE
oxigrad/__init__.py
oxigrad/_core.pyd
oxigrad/_core.pyi
oxigrad/py.typed
oxigrad-0.3.2.dist-info/RECORD
