Metadata-Version: 2.4
Name: oxigrad
Version: 0.3.2
Classifier: Development Status :: 4 - Beta
Classifier: Intended Audience :: Developers
Classifier: Intended Audience :: Education
Classifier: License :: OSI Approved :: MIT License
Classifier: Natural Language :: English
Classifier: Programming Language :: Rust
Classifier: Programming Language :: Python :: 3.9
Classifier: Programming Language :: Python :: 3.10
Classifier: Programming Language :: Python :: 3.11
Classifier: Programming Language :: Python :: 3.12
Classifier: Programming Language :: Python :: 3.13
Classifier: Topic :: Software Development :: Libraries
Classifier: Topic :: Utilities
Classifier: Typing :: Typed
License-File: LICENSE
Summary: A minimal scalar-valued autograd engine written in Rust
Home-Page: https://github.com/lalitm1004/oxigrad
Author-email: lalitm1004 <lalitm1004@gmail.com>
License: MIT
Requires-Python: >=3.9
Project-URL: Repository, https://github.com/lalitm1004/oxigrad
Project-URL: Homepage, https://github.com/lalitm1004/oxigrad
Project-URL: Issues, https://github.com/lalitm1004/oxigrad/issues
